{
  "latest_version": "1.13.3",
  "release_date": "2026-06-15",
  "download_url": "https://github.com/KamilMordarski/planora/releases/download/v1.13.3/Planora-Windows.zip",
  "download_urls": {
    "windows": "https://github.com/KamilMordarski/planora/releases/download/v1.13.3/Planora-Windows.zip",
    "macos": "https://github.com/KamilMordarski/planora/releases/download/v1.13.3/Planora-macOS.zip"
  },
  "notes": [
    "Sprzątanie sali, modlitwy i prowadzenie zbiórki nie wywołują już kolizji",
    "Naprawiono odświeżanie wybranych projektów w Centrum projektów",
    "Usunięto niedziałającego Asystenta planowania z aplikacji i dokumentacji"
  ]
}
